wii_music_editor/__init__.py
wii_music_editor/__main__.py
wii_music_editor/data/__init__.py
wii_music_editor/data/instruments.py
wii_music_editor/data/region.py
wii_music_editor/data/songs.py
wii_music_editor/data/styles.py
wii_music_editor/editor/__init__.py
wii_music_editor/editor/_brsar.py
wii_music_editor/editor/brsar.py
wii_music_editor/editor/dol.py
wii_music_editor/editor/editor.py
wii_music_editor/editor/message.py
wii_music_editor/editor/midi.py
wii_music_editor/editor/reset.py
wii_music_editor/editor/rom.py
wii_music_editor/editor/rom_folder.py
wii_music_editor/include/all/fonts/contb.ttf
wii_music_editor/include/all/fonts/contm.ttf
wii_music_editor/include/all/icon/icon.icns
wii_music_editor/include/all/icon/icon.ico
wii_music_editor/include/all/icon/icon.png
wii_music_editor/include/all/icon/iconBackground.png
wii_music_editor/include/all/save/RPClipDB.dat
wii_music_editor/include/all/save/RPMusic.dat
wii_music_editor/include/all/save/RPNandDB.dat
wii_music_editor/include/all/save/banner.bin
wii_music_editor/include/all/save/wc24scr.vff
wii_music_editor/include/windows/sequence_cmd/GotaSequenceCmd.exe
wii_music_editor/include/windows/sequence_cmd/GotaSequenceLib.dll
wii_music_editor/include/windows/sequence_cmd/GotaSoundIO.dll
wii_music_editor/include/windows/sequence_cmd/NAudio.dll
wii_music_editor/include/windows/sequence_cmd/Sanford.Multimedia.Midi.dll
wii_music_editor/include/windows/sequence_cmd/VGAudio.dll
wii_music_editor/include/windows/wiimms/cygcrypto-1.1.dll
wii_music_editor/include/windows/wiimms/cygncursesw-10.dll
wii_music_editor/include/windows/wiimms/cygpng16-16.dll
wii_music_editor/include/windows/wiimms/cygwin1.dll
wii_music_editor/include/windows/wiimms/cygz.dll
wii_music_editor/include/windows/wiimms/wbmgt.exe
wii_music_editor/include/windows/wiimms/wit.exe
wii_music_editor/include/windows/wiimms/wstrt.exe
wii_music_editor/include/windows/wiimms/wszst.exe
wii_music_editor/services/__init__.py
wii_music_editor/services/discord.py
wii_music_editor-2.0.0.dev11.dist-info/LICENSE
wii_music_editor-2.0.0.dev11.dist-info/METADATA
wii_music_editor-2.0.0.dev11.dist-info/WHEEL
wii_music_editor-2.0.0.dev11.dist-info/entry_points.txt
wii_music_editor-2.0.0.dev11.dist-info/top_level.txt
wii_music_editor-2.0.0.dev11.dist-info/RECORD
