Metadata-Version: 2.1
Name: wii_music_editor
Version: 2.0.0.dev11
Summary: The ultimate Wii Music modding tool
Author: Benjamin Halko
License: MIT License
Project-URL: Homepage, https://github.com/BenjaminHalko/WiiMusicEditorPlus
Project-URL: Discord, https://discord.gg/NC3wYAeCDs
Project-URL: Changelog, https://github.com/BenjaminHalko/WiiMusicEditorPlus/blob/dev/CHANGELOG.md
Project-URL: Wiki, https://github.com/BenjaminHalko/WiiMusicEditorPlus/wiki
Requires-Python: <3.13,>=3.9
License-File: LICENSE
Requires-Dist: importlib_metadata
Requires-Dist: mido
Requires-Dist: packaging
Requires-Dist: pretty_midi
Requires-Dist: psutil
Requires-Dist: pypresence
Requires-Dist: pyside6
Requires-Dist: requests
Requires-Dist: setuptools
